[
  {
    "pk": 1,
    "model": "fund.givingproject",
    "fields": {
      "suggested_steps": "Talk to about project\nInvite to SJF event\nSet up time to meet for the ask\nAsk\nFollow up\nThank",
      "title": "Tourmania Giving Project",
      "fund_goal": 2490,
      "pre_approved": "",
      "fundraising_deadline": "2000-01-01",
      "site_visits": false,
      "calendar": "fake.calendar.link",
      "public": true,
      "fundraising_training": "2001-12-31T01:00:00Z"
    }
  },
  {
    "pk": 2,
    "model": "fund.givingproject",
    "fields": {
      "suggested_steps": "Talk to about project\nInvite to SJF event\nSet up time to meet for the ask\nAsk\nFollow up\nThank",
      "title": "Geoform Giving Project",
      "fund_goal": 10691,
      "pre_approved": "",
      "fundraising_deadline": "2000-01-01",
      "site_visits": false,
      "calendar": "fake.calendar.link",
      "public": true,
      "fundraising_training": "2001-12-31T01:00:00Z"
    }
  },
  {
    "pk": 3,
    "model": "fund.givingproject",
    "fields": {
      "suggested_steps": "Talk to about project\nInvite to SJF event\nSet up time to meet for the ask\nAsk\nFollow up\nThank",
      "title": "Prosely Giving Project",
      "fund_goal": 9062,
      "pre_approved": "",
      "fundraising_deadline": "2000-01-01",
      "site_visits": false,
      "calendar": "fake.calendar.link",
      "public": true,
      "fundraising_training": "2001-12-31T01:00:00Z"
    }
  },
  {
    "pk": 4,
    "model": "fund.givingproject",
    "fields": {
      "suggested_steps": "Talk to about project\nInvite to SJF event\nSet up time to meet for the ask\nAsk\nFollow up\nThank",
      "title": "Eclipsent Giving Project",
      "fund_goal": 19655,
      "pre_approved": "",
      "fundraising_deadline": "2000-01-01",
      "site_visits": false,
      "calendar": "fake.calendar.link",
      "public": true,
      "fundraising_training": "2001-12-31T01:00:00Z"
    }
  },
  {
    "pk": 5,
    "model": "fund.givingproject",
    "fields": {
      "suggested_steps": "Talk to about project\nInvite to SJF event\nSet up time to meet for the ask\nAsk\nFollow up\nThank",
      "title": "Steelfab Giving Project",
      "fund_goal": 21230,
      "pre_approved": "",
      "fundraising_deadline": "2000-01-01",
      "site_visits": false,
      "calendar": "fake.calendar.link",
      "public": true,
      "fundraising_training": "2001-12-31T01:00:00Z"
    }
  },
  {
    "pk": 6,
    "model": "fund.givingproject",
    "fields": {
      "suggested_steps": "Talk to about project\nInvite to SJF event\nSet up time to meet for the ask\nAsk\nFollow up\nThank",
      "title": "Edecine Giving Project",
      "fund_goal": 9187,
      "pre_approved": "",
      "fundraising_deadline": "2000-01-01",
      "site_visits": false,
      "calendar": "fake.calendar.link",
      "public": true,
      "fundraising_training": "2001-12-31T01:00:00Z"
    }
  }
]
